<?xml version="1.0" encoding="utf-8"?>
<languageexport>
  <languagegroup>
    <lang>
      <word_app>trackmembers</word_app>
      <word_pack>public_trackmembers</word_pack>
      <word_key>tm_post</word_key>
      <word_default>post</word_default>
    </lang>
    <lang>
      <word_app>trackmembers</word_app>
      <word_pack>public_trackmembers</word_pack>
      <word_key>sort_submit</word_key>
      <word_default>Update filter</word_default>
    </lang>
    <lang>
      <word_app>trackmembers</word_app>
      <word_pack>public_trackmembers</word_pack>
      <word_key>sort_by_date</word_key>
      <word_default>Date</word_default>
    </lang>
    <lang>
      <word_app>trackmembers</word_app>
      <word_pack>public_trackmembers</word_pack>
      <word_key>sort_by_app</word_key>
      <word_default>Action</word_default>
    </lang>
    <lang>
      <word_app>trackmembers</word_app>
      <word_pack>public_trackmembers</word_pack>
      <word_key>sign_out</word_key>
      <word_default>Sign Out</word_default>
    </lang>
    <lang>
      <word_app>trackmembers</word_app>
      <word_pack>public_trackmembers</word_pack>
      <word_key>sign_in</word_key>
      <word_default>Sign In</word_default>
    </lang>
    <lang>
      <word_app>trackmembers</word_app>
      <word_pack>public_trackmembers</word_pack>
      <word_key>show_log_type</word_key>
      <word_default>Show log type</word_default>
    </lang>
    <lang>
      <word_app>trackmembers</word_app>
      <word_pack>public_trackmembers</word_pack>
      <word_key>sent_pm</word_key>
      <word_default>Sent a Private Message to %s</word_default>
    </lang>
    <lang>
      <word_app>trackmembers</word_app>
      <word_pack>public_trackmembers</word_pack>
      <word_key>save</word_key>
      <word_default>Save</word_default>
    </lang>
    <lang>
      <word_app>trackmembers</word_app>
      <word_pack>public_trackmembers</word_pack>
      <word_key>reputation_system</word_key>
      <word_default>Reputation Point (posts)</word_default>
    </lang>
    <lang>
      <word_app>trackmembers</word_app>
      <word_pack>public_trackmembers</word_pack>
      <word_key>reputation_point</word_key>
      <word_default>Gave a %s reputation point to a %s on topic: %s</word_default>
    </lang>
    <lang>
      <word_app>trackmembers</word_app>
      <word_pack>public_trackmembers</word_pack>
      <word_key>reply_topic</word_key>
      <word_default>New Reply</word_default>
    </lang>
    <lang>
      <word_app>trackmembers</word_app>
      <word_pack>public_trackmembers</word_pack>
      <word_key>edit_post</word_key>
      <word_default>Edit Post</word_default>
    </lang>
    <lang>
      <word_app>trackmembers</word_app>
      <word_pack>public_trackmembers</word_pack>
      <word_key>reply_su</word_key>
      <word_default>Reply Status Update</word_default>
    </lang>
    <lang>
      <word_app>trackmembers</word_app>
      <word_pack>public_trackmembers</word_pack>
      <word_key>reply_pm</word_key>
      <word_default>Private Message Reply</word_default>
    </lang>
    <lang>
      <word_app>trackmembers</word_app>
      <word_pack>public_trackmembers</word_pack>
      <word_key>replied_pm</word_key>
      <word_default>Replied to a Private Message between %s and %s</word_default>
    </lang>
    <lang>
      <word_app>trackmembers</word_app>
      <word_pack>public_trackmembers</word_pack>
      <word_key>removed_friend_desc</word_key>
      <word_default><![CDATA[Deleted <a href='%s'>%s</a> as a friend]]></word_default>
    </lang>
    <lang>
      <word_app>trackmembers</word_app>
      <word_pack>public_trackmembers</word_pack>
      <word_key>removed_friend</word_key>
      <word_default>Deleted friend</word_default>
    </lang>
    <lang>
      <word_app>trackmembers</word_app>
      <word_pack>public_trackmembers</word_pack>
      <word_key>profile_visited</word_key>
      <word_default>Profile visited: %s</word_default>
    </lang>
    <lang>
      <word_app>trackmembers</word_app>
      <word_pack>public_trackmembers</word_pack>
      <word_key>profile_updated</word_key>
      <word_default>Profile updated</word_default>
    </lang>
    <lang>
      <word_app>trackmembers</word_app>
      <word_pack>public_trackmembers</word_pack>
      <word_key>profile_actions</word_key>
      <word_default>Profile Actions</word_default>
    </lang>
    <lang>
      <word_app>trackmembers</word_app>
      <word_pack>public_trackmembers</word_pack>
      <word_key>downloads_actions</word_key>
      <word_default>Downloads Actions</word_default>
    </lang>
    <lang>
      <word_app>trackmembers</word_app>
      <word_pack>public_trackmembers</word_pack>
      <word_key>new_topic</word_key>
      <word_default>Created a topic called %s on forum %s</word_default>
    </lang>
    <lang>
      <word_app>trackmembers</word_app>
      <word_pack>public_trackmembers</word_pack>
      <word_key>post_edited</word_key>
      <word_default>Edited the post %s from topic %s</word_default>
    </lang>
    <lang>
      <word_app>trackmembers</word_app>
      <word_pack>public_trackmembers</word_pack>
      <word_key>new_su</word_key>
      <word_default>New Status Update</word_default>
    </lang>
    <lang>
      <word_app>trackmembers</word_app>
      <word_pack>public_trackmembers</word_pack>
      <word_key>new_statusupdate_reply</word_key>
      <word_default><![CDATA[Made a reply to a <a href='%s'>status update</a>]]></word_default>
    </lang>
    <lang>
      <word_app>trackmembers</word_app>
      <word_pack>public_trackmembers</word_pack>
      <word_key>new_statusupdate</word_key>
      <word_default><![CDATA[Posted a new <a href='%s'>status update</a> ]]></word_default>
    </lang>
    <lang>
      <word_app>trackmembers</word_app>
      <word_pack>public_trackmembers</word_pack>
      <word_key>new_reply</word_key>
      <word_default>Posted a reply on topic: %s</word_default>
    </lang>
    <lang>
      <word_app>trackmembers</word_app>
      <word_pack>public_trackmembers</word_pack>
      <word_key>new_pm</word_key>
      <word_default>New Private Message</word_default>
    </lang>
    <lang>
      <word_app>trackmembers</word_app>
      <word_pack>public_trackmembers</word_pack>
      <word_key>new_friend_desc</word_key>
      <word_default><![CDATA[Added <a href='%s'>%s</a> as a friend]]></word_default>
    </lang>
    <lang>
      <word_app>trackmembers</word_app>
      <word_pack>public_trackmembers</word_pack>
      <word_key>new_friend</word_key>
      <word_default>New friend</word_default>
    </lang>
    <lang>
      <word_app>trackmembers</word_app>
      <word_pack>public_trackmembers</word_pack>
      <word_key>logfilter_all</word_key>
      <word_default>Show All</word_default>
    </lang>
    <lang>
      <word_app>trackmembers</word_app>
      <word_pack>public_trackmembers</word_pack>
      <word_key>like_system</word_key>
      <word_default>Like System (posts)</word_default>
    </lang>
    <lang>
      <word_app>trackmembers</word_app>
      <word_pack>public_trackmembers</word_pack>
      <word_key>liked_post</word_key>
      <word_default>Liked a %s on topic: %s</word_default>
    </lang>
    <lang>
      <word_app>trackmembers</word_app>
      <word_pack>public_trackmembers</word_pack>
      <word_key>forum_actions</word_key>
      <word_default>Forum Actions</word_default>
    </lang>
    <lang>
      <word_app>trackmembers</word_app>
      <word_pack>public_trackmembers</word_pack>
      <word_key>follow_topicforum</word_key>
      <word_default>Follow Topic / Forum</word_default>
    </lang>
    <lang>
      <word_app>trackmembers</word_app>
      <word_pack>public_trackmembers</word_pack>
      <word_key>follow_topic</word_key>
      <word_default>Follow Topic</word_default>
    </lang>
    <lang>
      <word_app>trackmembers</word_app>
      <word_pack>public_trackmembers</word_pack>
      <word_key>follow_forum</word_key>
      <word_default>Follow Forum</word_default>
    </lang>
    <lang>
      <word_app>trackmembers</word_app>
      <word_pack>public_trackmembers</word_pack>
      <word_key>followed_topic</word_key>
      <word_default>Followed a topic: %s</word_default>
    </lang>
    <lang>
      <word_app>trackmembers</word_app>
      <word_pack>public_trackmembers</word_pack>
      <word_key>followed_forum</word_key>
      <word_default>Followed a forum: %s</word_default>
    </lang>
    <lang>
      <word_app>trackmembers</word_app>
      <word_pack>public_trackmembers</word_pack>
      <word_key>filter_sort</word_key>
      <word_default>Sort by</word_default>
    </lang>
    <lang>
      <word_app>trackmembers</word_app>
      <word_pack>public_trackmembers</word_pack>
      <word_key>filter_direction</word_key>
      <word_default>Sort direction</word_default>
    </lang>
    <lang>
      <word_app>trackmembers</word_app>
      <word_pack>public_trackmembers</word_pack>
      <word_key>do_logout</word_key>
      <word_default>Signed out of the board</word_default>
    </lang>
    <lang>
      <word_app>trackmembers</word_app>
      <word_pack>public_trackmembers</word_pack>
      <word_key>do_login</word_key>
      <word_default>Signed in on the board</word_default>
    </lang>
    <lang>
      <word_app>trackmembers</word_app>
      <word_pack>public_trackmembers</word_pack>
      <word_key>descending_order</word_key>
      <word_default>Descending (Z-A)</word_default>
    </lang>
    <lang>
      <word_app>trackmembers</word_app>
      <word_pack>public_trackmembers</word_pack>
      <word_key>delete_su_reply</word_key>
      <word_default>Delete Status Update Reply</word_default>
    </lang>
    <lang>
      <word_app>trackmembers</word_app>
      <word_pack>public_trackmembers</word_pack>
      <word_key>delete_su</word_key>
      <word_default>Delete Status Update</word_default>
    </lang>
    <lang>
      <word_app>trackmembers</word_app>
      <word_pack>public_trackmembers</word_pack>
      <word_key>delete_statusupdate</word_key>
      <word_default>Deleted a status update</word_default>
    </lang>
    <lang>
      <word_app>trackmembers</word_app>
      <word_pack>public_trackmembers</word_pack>
      <word_key>create_topic</word_key>
      <word_default>New Topic</word_default>
    </lang>
    <lang>
      <word_app>trackmembers</word_app>
      <word_pack>public_trackmembers</word_pack>
      <word_key>edit_post</word_key>
      <word_default>Edit Post</word_default>
    </lang>
    <lang>
      <word_app>trackmembers</word_app>
      <word_pack>public_trackmembers</word_pack>
      <word_key>change_pw</word_key>
      <word_default>Change Password</word_default>
    </lang>
    <lang>
      <word_app>trackmembers</word_app>
      <word_pack>public_trackmembers</word_pack>
      <word_key>change_email</word_key>
      <word_default>Change Email Address</word_default>
    </lang>
    <lang>
      <word_app>trackmembers</word_app>
      <word_pack>public_trackmembers</word_pack>
      <word_key>change_dn</word_key>
      <word_default>Change Display Name</word_default>
    </lang>
    <lang>
      <word_app>trackmembers</word_app>
      <word_pack>public_trackmembers</word_pack>
      <word_key>changed_username</word_key>
      <word_default><![CDATA[Display Name changed to '%s']]></word_default>
    </lang>
    <lang>
      <word_app>trackmembers</word_app>
      <word_pack>public_trackmembers</word_pack>
      <word_key>changed_password</word_key>
      <word_default>Password changed</word_default>
    </lang>
    <lang>
      <word_app>trackmembers</word_app>
      <word_pack>public_trackmembers</word_pack>
      <word_key>changed_email</word_key>
      <word_default><![CDATA[Email changed from '%s' to '%s']]></word_default>
    </lang>
    <lang>
      <word_app>trackmembers</word_app>
      <word_pack>public_trackmembers</word_pack>
      <word_key>ascending_order</word_key>
      <word_default>Ascending (A-Z)</word_default>
    </lang>
    <lang>
      <word_app>trackmembers</word_app>
      <word_pack>public_trackmembers</word_pack>
      <word_key>all_types</word_key>
      <word_default>All types</word_default>
    </lang>
    <lang>
      <word_app>trackmembers</word_app>
      <word_pack>public_trackmembers</word_pack>
      <word_key>account_actions</word_key>
      <word_default>Account Actions</word_default>
    </lang>
    <lang>
      <word_app>trackmembers</word_app>
      <word_pack>public_trackmembers</word_pack>
      <word_key>topic_viewed</word_key>
      <word_default>Viewed a topic: %s</word_default>
    </lang>
    <lang>
      <word_app>trackmembers</word_app>
      <word_pack>public_trackmembers</word_pack>
      <word_key>tracking_logs_from</word_key>
      <word_default>Viewing Tracking Logs from</word_default>
    </lang>
    <lang>
      <word_app>trackmembers</word_app>
      <word_pack>public_trackmembers</word_pack>
      <word_key>tracking_member</word_key>
      <word_default>This member is being tracked now!</word_default>
    </lang>
    <lang>
      <word_app>trackmembers</word_app>
      <word_pack>public_trackmembers</word_pack>
      <word_key>track_change_settings</word_key>
      <word_default>Change track settings</word_default>
    </lang>
    <lang>
      <word_app>trackmembers</word_app>
      <word_pack>public_trackmembers</word_pack>
      <word_key>track_memberid</word_key>
      <word_default>Member ID:</word_default>
    </lang>
    <lang>
      <word_app>trackmembers</word_app>
      <word_pack>public_trackmembers</word_pack>
      <word_key>track_members</word_key>
      <word_default>Track Members</word_default>
    </lang>
    <lang>
      <word_app>trackmembers</word_app>
      <word_pack>public_trackmembers</word_pack>
      <word_key>track_nologs</word_key>
      <word_default><![CDATA[There are no entries for this Member's log]]></word_default>
    </lang>
    <lang>
      <word_app>trackmembers</word_app>
      <word_pack>public_trackmembers</word_pack>
      <word_key>track_stop_tracking</word_key>
      <word_default>Stop tracking this member</word_default>
    </lang>
    <lang>
      <word_app>trackmembers</word_app>
      <word_pack>public_trackmembers</word_pack>
      <word_key>track_stop_tracking_short</word_key>
      <word_default>Stop tracking</word_default>
    </lang>
    <lang>
      <word_app>trackmembers</word_app>
      <word_pack>public_trackmembers</word_pack>
      <word_key>track_this_member</word_key>
      <word_default>Track this member</word_default>
    </lang>
    <lang>
      <word_app>trackmembers</word_app>
      <word_pack>public_trackmembers</word_pack>
      <word_key>track_view_logs</word_key>
      <word_default>View tracking logs</word_default>
    </lang>
    <lang>
      <word_app>trackmembers</word_app>
      <word_pack>public_trackmembers</word_pack>
      <word_key>unliked_post</word_key>
      <word_default>Unliked a %s post on topic: %s</word_default>
    </lang>
    <lang>
      <word_app>trackmembers</word_app>
      <word_pack>public_trackmembers</word_pack>
      <word_key>untracked_member</word_key>
      <word_default>This member is not being tracked anymore</word_default>
    </lang>
    <lang>
      <word_app>trackmembers</word_app>
      <word_pack>public_trackmembers</word_pack>
      <word_key>viewing_tracking_logs</word_key>
      <word_default>Viewing Tracking Logs</word_default>
    </lang>
    <lang>
      <word_app>trackmembers</word_app>
      <word_pack>public_trackmembers</word_pack>
      <word_key>view_profile</word_key>
      <word_default>View Profile</word_default>
    </lang>
    <lang>
      <word_app>trackmembers</word_app>
      <word_pack>public_trackmembers</word_pack>
      <word_key>view_topic</word_key>
      <word_default>View Topic</word_default>
    </lang>
    <lang>
      <word_app>trackmembers</word_app>
      <word_pack>public_trackmembers</word_pack>
      <word_key>back_to_profile</word_key>
      <word_default>Back to Profile</word_default>
    </lang>
    <lang>
      <word_app>trackmembers</word_app>
      <word_pack>public_trackmembers</word_pack>
      <word_key>filter_date</word_key>
      <word_default>Date</word_default>
    </lang>
    <lang>
      <word_app>trackmembers</word_app>
      <word_pack>public_trackmembers</word_pack>
      <word_key>filter_action</word_key>
      <word_default>Action</word_default>
    </lang>
    <lang>
      <word_app>trackmembers</word_app>
      <word_pack>public_trackmembers</word_pack>
      <word_key>ip_address</word_key>
      <word_default>IP Address</word_default>
    </lang>
    <lang>
      <word_app>trackmembers</word_app>
      <word_pack>public_trackmembers</word_pack>
      <word_key>filter_custom</word_key>
      <word_default>Custom</word_default>
    </lang>
    <lang>
      <word_app>trackmembers</word_app>
      <word_pack>public_trackmembers</word_pack>
      <word_key>filter_description</word_key>
      <word_default>Description</word_default>
    </lang>
    <lang>
      <word_app>trackmembers</word_app>
      <word_pack>public_trackmembers</word_pack>
      <word_key>tracking_setup_for</word_key>
      <word_default>Tracking setup for</word_default>
    </lang>
    <lang>
      <word_app>trackmembers</word_app>
      <word_pack>public_trackmembers</word_pack>
      <word_key>track</word_key>
      <word_default>Track</word_default>
    </lang>
    <lang>
      <word_app>trackmembers</word_app>
      <word_pack>public_trackmembers</word_pack>
      <word_key>track_for</word_key>
      <word_default>for</word_default>
    </lang>
    <lang>
      <word_app>trackmembers</word_app>
      <word_pack>public_trackmembers</word_pack>
      <word_key>track_days</word_key>
      <word_default>days</word_default>
    </lang>
    <lang>
      <word_app>trackmembers</word_app>
      <word_pack>public_trackmembers</word_pack>
      <word_key>track_infinitively</word_key>
      <word_default><![CDATA[Enter -1 to track member infinitively]]></word_default>
    </lang>
    <lang>
      <word_app>trackmembers</word_app>
      <word_pack>public_trackmembers</word_pack>
      <word_key>add_file</word_key>
      <word_default>Upload File</word_default>
    </lang>
    <lang>
      <word_app>trackmembers</word_app>
      <word_pack>public_trackmembers</word_pack>
      <word_key>edit_file</word_key>
      <word_default>Edit File</word_default>
    </lang>
    <lang>
      <word_app>trackmembers</word_app>
      <word_pack>public_trackmembers</word_pack>
      <word_key>follow_file</word_key>
      <word_default>Follow File</word_default>
    </lang>
    <lang>
      <word_app>trackmembers</word_app>
      <word_pack>public_trackmembers</word_pack>
      <word_key>followed_file</word_key>
      <word_default>Followed a file: %s</word_default>
    </lang>
    <lang>
      <word_app>trackmembers</word_app>
      <word_pack>public_trackmembers</word_pack>
      <word_key>added_file</word_key>
      <word_default>File uploaded: %s</word_default>
    </lang>
    <lang>
      <word_app>trackmembers</word_app>
      <word_pack>public_trackmembers</word_pack>
      <word_key>edited_file</word_key>
      <word_default>File edited: %s</word_default>
    </lang>
    <lang>
      <word_app>trackmembers</word_app>
      <word_pack>public_trackmembers</word_pack>
      <word_key>add_file_comment</word_key>
      <word_default>Submit File Review</word_default>
    </lang>
    <lang>
      <word_app>trackmembers</word_app>
      <word_pack>public_trackmembers</word_pack>
      <word_key>added_file_comment</word_key>
      <word_default><![CDATA[Submitted a <a href='%s'>review</a> to file: %s]]></word_default>
    </lang>
    <lang>
      <word_app>trackmembers</word_app>
      <word_pack>public_trackmembers</word_pack>
      <word_key>report_file_broken</word_key>
      <word_default>Report a File as Broken</word_default>
    </lang>
    <lang>
      <word_app>trackmembers</word_app>
      <word_pack>public_trackmembers</word_pack>
      <word_key>reported_file_broken</word_key>
      <word_default>Reported a file as brokne: %s</word_default>
    </lang>
    <lang>
      <word_app>trackmembers</word_app>
      <word_pack>public_trackmembers</word_pack>
      <word_key>gallery_actions</word_key>
      <word_default>Gallery Actions</word_default>
    </lang>
    <lang>
      <word_app>trackmembers</word_app>
      <word_pack>public_trackmembers</word_pack>
      <word_key>create_album</word_key>
      <word_default>Create Album</word_default>
    </lang>
    <lang>
      <word_app>trackmembers</word_app>
      <word_pack>public_trackmembers</word_pack>
      <word_key>created_album</word_key>
      <word_default>Album Created: %s</word_default>
    </lang>
    <lang>
      <word_app>trackmembers</word_app>
      <word_pack>public_trackmembers</word_pack>
      <word_key>add_image</word_key>
      <word_default>Publish Image/Media</word_default>
    </lang>
    <lang>
      <word_app>trackmembers</word_app>
      <word_pack>public_trackmembers</word_pack>
      <word_key>added_image</word_key>
      <word_default>Image/Media published: %s</word_default>
    </lang>
    <lang>
      <word_app>trackmembers</word_app>
      <word_pack>public_trackmembers</word_pack>
      <word_key>edit_image</word_key>
      <word_default>Edit Image/Media</word_default>
    </lang>
    <lang>
      <word_app>trackmembers</word_app>
      <word_pack>public_trackmembers</word_pack>
      <word_key>edited_image</word_key>
      <word_default>Image/Media edited: %s</word_default>
    </lang>
    <lang>
      <word_app>trackmembers</word_app>
      <word_pack>public_trackmembers</word_pack>
      <word_key>follow_image</word_key>
      <word_default>Follow Image/Media</word_default>
    </lang>
    <lang>
      <word_app>trackmembers</word_app>
      <word_pack>public_trackmembers</word_pack>
      <word_key>followed_image</word_key>
      <word_default>Followed an image/media: %s</word_default>
    </lang>
    <lang>
      <word_app>trackmembers</word_app>
      <word_pack>public_trackmembers</word_pack>
      <word_key>liked_img</word_key>
      <word_default>Liked an image/media: %s</word_default>
    </lang>
    <lang>
      <word_app>trackmembers</word_app>
      <word_pack>public_trackmembers</word_pack>
      <word_key>unliked_img</word_key>
      <word_default>Unliked an image/media: %s</word_default>
    </lang>
    <lang>
      <word_app>trackmembers</word_app>
      <word_pack>public_trackmembers</word_pack>
      <word_key>img_reputation_point</word_key>
      <word_default>Gave a %s reputation point to the image/media: %s</word_default>
    </lang>
    <lang>
      <word_app>trackmembers</word_app>
      <word_pack>public_trackmembers</word_pack>
      <word_key>like_system_images</word_key>
      <word_default>Like System (image/media)</word_default>
    </lang>
    <lang>
      <word_app>trackmembers</word_app>
      <word_pack>public_trackmembers</word_pack>
      <word_key>reputation_system_images</word_key>
      <word_default>Reputation Point (image/media)</word_default>
    </lang>
    <lang>
      <word_app>trackmembers</word_app>
      <word_pack>public_trackmembers</word_pack>
      <word_key>like_system_comments</word_key>
      <word_default>Like System (image/media comments)</word_default>
    </lang>
    <lang>
      <word_app>trackmembers</word_app>
      <word_pack>public_trackmembers</word_pack>
      <word_key>reputation_system_comments</word_key>
      <word_default>Reputation Point (image/media comments)</word_default>
    </lang>
    <lang>
      <word_app>trackmembers</word_app>
      <word_pack>public_trackmembers</word_pack>
      <word_key>liked_img_comment</word_key>
      <word_default><![CDATA[Liked a <a href='%s'>comment</a> in image/media: %s]]></word_default>
    </lang>
    <lang>
      <word_app>trackmembers</word_app>
      <word_pack>public_trackmembers</word_pack>
      <word_key>img_reputation_point_comment</word_key>
      <word_default>Gave a %s reputation point to a comment of image/media: %s</word_default>
    </lang>
    <lang>
      <word_app>trackmembers</word_app>
      <word_pack>public_trackmembers</word_pack>
      <word_key>add_image_comment</word_key>
      <word_default>Submit Image Comment</word_default>
    </lang>
    <lang>
      <word_app>trackmembers</word_app>
      <word_pack>public_trackmembers</word_pack>
      <word_key>added_image_comment</word_key>
      <word_default><![CDATA[Submitted a <a href='%s'>comment</a> to image: %s]]></word_default>
    </lang>
    <lang>
      <word_app>trackmembers</word_app>
      <word_pack>public_trackmembers</word_pack>
      <word_key>reputation_file_review</word_key>
      <word_default>Reputation Point (file reviews)</word_default>
    </lang>
    <lang>
      <word_app>trackmembers</word_app>
      <word_pack>public_trackmembers</word_pack>
      <word_key>like_system_file_review</word_key>
      <word_default>Like System (file reviews)</word_default>
    </lang>
    <lang>
      <word_app>trackmembers</word_app>
      <word_pack>public_trackmembers</word_pack>
      <word_key>reputation_file_review</word_key>
      <word_default>Reputation Points (file reviews)</word_default>
    </lang>
    <lang>
      <word_app>trackmembers</word_app>
      <word_pack>public_trackmembers</word_pack>
      <word_key>added_reputation_file_review</word_key>
      <word_default><![CDATA[Gave a %s reputation point to a <a href='%s'>review</a> on file: %s]]></word_default>
    </lang>
    <lang>
      <word_app>trackmembers</word_app>
      <word_pack>public_trackmembers</word_pack>
      <word_key>like_file_review</word_key>
      <word_default><![CDATA[Liked a <a href='%s'>review</a> to file: %s]]></word_default>
    </lang>
    <lang>
      <word_app>trackmembers</word_app>
      <word_pack>public_trackmembers</word_pack>
      <word_key>create_blog</word_key>
      <word_default>Create Blog</word_default>
    </lang>
    <lang>
      <word_app>trackmembers</word_app>
      <word_pack>public_trackmembers</word_pack>
      <word_key>add_entry</word_key>
      <word_default>Post Entry</word_default>
    </lang>
    <lang>
      <word_app>trackmembers</word_app>
      <word_pack>public_trackmembers</word_pack>
      <word_key>edit_entry</word_key>
      <word_default>Edit Entry</word_default>
    </lang>
    <lang>
      <word_app>trackmembers</word_app>
      <word_pack>public_trackmembers</word_pack>
      <word_key>add_entry_comment</word_key>
      <word_default>Submit Entry Comment</word_default>
    </lang>
    <lang>
      <word_app>trackmembers</word_app>
      <word_pack>public_trackmembers</word_pack>
      <word_key>like_system_entry</word_key>
      <word_default>Like System (entry)</word_default>
    </lang>
    <lang>
      <word_app>trackmembers</word_app>
      <word_pack>public_trackmembers</word_pack>
      <word_key>like_system_entry_comments</word_key>
      <word_default>Like System (entry comment)</word_default>
    </lang>
    <lang>
      <word_app>trackmembers</word_app>
      <word_pack>public_trackmembers</word_pack>
      <word_key>like_system_entry</word_key>
      <word_default>Like System (entry)</word_default>
    </lang>
    <lang>
      <word_app>trackmembers</word_app>
      <word_pack>public_trackmembers</word_pack>
      <word_key>reputation_system_entry</word_key>
      <word_default>Reputation System (entry)</word_default>
    </lang>
     <lang>
      <word_app>trackmembers</word_app>
      <word_pack>public_trackmembers</word_pack>
      <word_key>reputation_system_entry_comments</word_key>
      <word_default>Reputation System (entry comment)</word_default>
    </lang>
     <lang>
      <word_app>trackmembers</word_app>
      <word_pack>public_trackmembers</word_pack>
      <word_key>follow_entry</word_key>
      <word_default>Follow Entry</word_default>
    </lang>
    <lang>
      <word_app>trackmembers</word_app>
      <word_pack>public_trackmembers</word_pack>
      <word_key>blog_actions</word_key>
      <word_default>Blogs Actions</word_default>
    </lang>
    <lang>
      <word_app>trackmembers</word_app>
      <word_pack>public_trackmembers</word_pack>
      <word_key>created_blog</word_key>
      <word_default>Blog created: %s</word_default>
    </lang>
    <lang>
      <word_app>trackmembers</word_app>
      <word_pack>public_trackmembers</word_pack>
      <word_key>added_entry</word_key>
      <word_default>Entry posted: %s</word_default>
    </lang>
    <lang>
      <word_app>trackmembers</word_app>
      <word_pack>public_trackmembers</word_pack>
      <word_key>added_entry_comment</word_key>
      <word_default><![CDATA[Submitted a <a href='%s'>comment</a> to a blog entry: %s]]></word_default>
    </lang>
    <lang>
      <word_app>trackmembers</word_app>
      <word_pack>public_trackmembers</word_pack>
      <word_key>liked_entry</word_key>
      <word_default>Liked a blog entry: %s</word_default>
    </lang>
    <lang>
      <word_app>trackmembers</word_app>
      <word_pack>public_trackmembers</word_pack>
      <word_key>liked_entry</word_key>
      <word_default>Liked a blog entry: %s</word_default>
    </lang>
    <lang>
      <word_app>trackmembers</word_app>
      <word_pack>public_trackmembers</word_pack>
      <word_key>unliked_entry</word_key>
      <word_default>Unliked a blog entry: %s</word_default>
    </lang>
    <lang>
      <word_app>trackmembers</word_app>
      <word_pack>public_trackmembers</word_pack>
      <word_key>entry_reputation_point</word_key>
      <word_default>Gave a %s reputation point to the blog entry: %s</word_default>
    </lang>
    <lang>
      <word_app>trackmembers</word_app>
      <word_pack>public_trackmembers</word_pack>
      <word_key>reputation_system_entry</word_key>
      <word_default>Reputation Point (blog entry)</word_default>
    </lang>
    <lang>
      <word_app>trackmembers</word_app>
      <word_pack>public_trackmembers</word_pack>
      <word_key>like_system_entry</word_key>
      <word_default>Like System (blog entry)</word_default>
    </lang>
    <lang>
      <word_app>trackmembers</word_app>
      <word_pack>public_trackmembers</word_pack>
      <word_key>liked_entry_comment</word_key>
      <word_default><![CDATA[Liked a <a href='%s'>comment</a> on a blog entry: %s]]></word_default>
    </lang>
    <lang>
      <word_app>trackmembers</word_app>
      <word_pack>public_trackmembers</word_pack>
      <word_key>unliked_entry_comment</word_key>
      <word_default><![CDATA[Unliked a <a href='%s'>comment</a> on a blog entry: %s]]></word_default>
    </lang>
    <lang>
      <word_app>trackmembers</word_app>
      <word_pack>public_trackmembers</word_pack>
      <word_key>entry_reputation_point_comment</word_key>
      <word_default><![CDATA[Gave a %s reputation point to a <a href='%s'>comment</a> of the blog entry: %s]]></word_default>
    </lang>
    <lang>
      <word_app>trackmembers</word_app>
      <word_pack>public_trackmembers</word_pack>
      <word_key>followed_entry</word_key>
      <word_default>Followed a blog entry: %s</word_default>
    </lang>
    <lang>
      <word_app>trackmembers</word_app>
      <word_pack>public_trackmembers</word_pack>
      <word_key>classifieds_actions</word_key>
      <word_default>Classifieds Actions</word_default>
    </lang>
    <lang>
      <word_app>trackmembers</word_app>
      <word_pack>public_trackmembers</word_pack>
      <word_key>add_advert</word_key>
      <word_default>Add Advert</word_default>
    </lang>
    <lang>
      <word_app>trackmembers</word_app>
      <word_pack>public_trackmembers</word_pack>
      <word_key>added_advert</word_key>
      <word_default>Added an Advert: %s</word_default>
    </lang>
    <lang>
      <word_app>trackmembers</word_app>
      <word_pack>public_trackmembers</word_pack>
      <word_key>edit_advert</word_key>
      <word_default>Edit Advert</word_default>
    </lang>
    <lang>
      <word_app>trackmembers</word_app>
      <word_pack>public_trackmembers</word_pack>
      <word_key>edited_advert</word_key>
      <word_default>Edited an Advert: %s</word_default>
    </lang>
    <lang>
      <word_app>trackmembers</word_app>
      <word_pack>public_trackmembers</word_pack>
      <word_key>tutorials_actions</word_key>
      <word_default>Tutorials Actions</word_default>
    </lang>
    <lang>
      <word_app>trackmembers</word_app>
      <word_pack>public_trackmembers</word_pack>
      <word_key>add_tutorial</word_key>
      <word_default>Submit Tutorial</word_default>
    </lang>
    <lang>
      <word_app>trackmembers</word_app>
      <word_pack>public_trackmembers</word_pack>
      <word_key>edit_tutorial</word_key>
      <word_default>Edit Tutorial</word_default>
    </lang>
    <lang>
      <word_app>trackmembers</word_app>
      <word_pack>public_trackmembers</word_pack>
      <word_key>edited_tutorial</word_key>
      <word_default>Tutorial Edited: %s</word_default>
    </lang>
    <lang>
      <word_app>trackmembers</word_app>
      <word_pack>public_trackmembers</word_pack>
      <word_key>add_tutorial_comment</word_key>
      <word_default>Submit Tutorial Comment</word_default>
    </lang>
    <lang>
      <word_app>trackmembers</word_app>
      <word_pack>public_trackmembers</word_pack>
      <word_key>like_system_tutorials</word_key>
      <word_default>Like System (tutorial)</word_default>
    </lang>
    <lang>
      <word_app>trackmembers</word_app>
      <word_pack>public_trackmembers</word_pack>
      <word_key>like_system_tutorials_comments</word_key>
      <word_default>Like System (tutorial comments) </word_default>
    </lang>
    <lang>
      <word_app>trackmembers</word_app>
      <word_pack>public_trackmembers</word_pack>
      <word_key>reputation_system_tutorials</word_key>
      <word_default>Reputation Point (tutorial)</word_default>
    </lang>
    <lang>
      <word_app>trackmembers</word_app>
      <word_pack>public_trackmembers</word_pack>
      <word_key>reputation_system_tutorials_comments</word_key>
      <word_default>Reputation Point (tutorial comments)</word_default>
    </lang>
    <lang>
      <word_app>trackmembers</word_app>
      <word_pack>public_trackmembers</word_pack>
      <word_key>follow_tutorial</word_key>
      <word_default>Follow Tutorial</word_default>
    </lang>
    <lang>
      <word_app>trackmembers</word_app>
      <word_pack>public_trackmembers</word_pack>
      <word_key>followed_tutorial</word_key>
      <word_default>Followed a Tutorial: %s</word_default>
    </lang>
    <lang>
      <word_app>trackmembers</word_app>
      <word_pack>public_trackmembers</word_pack>
      <word_key>liked_tutorial</word_key>
      <word_default>Liked a Tutorial: %s</word_default>
    </lang>
    <lang>
      <word_app>trackmembers</word_app>
      <word_pack>public_trackmembers</word_pack>
      <word_key>unliked_tutorial</word_key>
      <word_default>Unliked a Tutorial: %s</word_default>
    </lang>
    <lang>
      <word_app>trackmembers</word_app>
      <word_pack>public_trackmembers</word_pack>
      <word_key>tutorial_reputation_point</word_key>
      <word_default>Gave a %s reputation point to a Tutorial: %s</word_default>
    </lang>
    <lang>
      <word_app>trackmembers</word_app>
      <word_pack>public_trackmembers</word_pack>
      <word_key>liked_tutorial_comment</word_key>
      <word_default><![CDATA[Liked a <a href='%s'>comment</a> in Tutorial: %s]]></word_default>
    </lang>
    <lang>
      <word_app>trackmembers</word_app>
      <word_pack>public_trackmembers</word_pack>
      <word_key>unliked_tutorial_comment</word_key>
      <word_default><![CDATA[Unliked a <a href='%s'>comment</a> in Tutorial: %s]]></word_default>
    </lang>
    <lang>
      <word_app>trackmembers</word_app>
      <word_pack>public_trackmembers</word_pack>
      <word_key>tutorial_comment_reputation_point</word_key>
      <word_default><![CDATA[Gave a %s reputation point to a <a href='%s'>comment</a> of Tutorial: %s]]></word_default>
    </lang>
    <lang>
      <word_app>trackmembers</word_app>
      <word_pack>public_trackmembers</word_pack>
      <word_key>added_tutorial_comment</word_key>
      <word_default><![CDATA[Submitted a <a href='%s'>comment</a> to a tutorial: %s]]></word_default>
    </lang>
    <lang>
      <word_app>trackmembers</word_app>
      <word_pack>public_trackmembers</word_pack>
      <word_key>added_tutorial</word_key>
      <word_default>Submitted a Tutorial: %s</word_default>
    </lang>
    <lang>
      <word_app>trackmembers</word_app>
      <word_pack>public_trackmembers</word_pack>
      <word_key>links_actions</word_key>
      <word_default>Links Actions</word_default>
    </lang>
    <lang>
      <word_app>trackmembers</word_app>
      <word_pack>public_trackmembers</word_pack>
      <word_key>add_link</word_key>
      <word_default>Submit Link</word_default>
    </lang>
    <lang>
      <word_app>trackmembers</word_app>
      <word_pack>public_trackmembers</word_pack>
      <word_key>added_link</word_key>
      <word_default>Submitted a Link: %s</word_default>
    </lang>
    <lang>
      <word_app>trackmembers</word_app>
      <word_pack>public_trackmembers</word_pack>
      <word_key>edit_link</word_key>
      <word_default>Edit Link</word_default>
    </lang>
    <lang>
      <word_app>trackmembers</word_app>
      <word_pack>public_trackmembers</word_pack>
      <word_key>edited_link</word_key>
      <word_default>Link Edited: %s</word_default>
    </lang>
    <lang>
      <word_app>trackmembers</word_app>
      <word_pack>public_trackmembers</word_pack>
      <word_key>add_link_comment</word_key>
      <word_default>Submit Link Comment</word_default>
    </lang>
    <lang>
      <word_app>trackmembers</word_app>
      <word_pack>public_trackmembers</word_pack>
      <word_key>like_system_links</word_key>
      <word_default>Like System (link)</word_default>
    </lang>
    <lang>
      <word_app>trackmembers</word_app>
      <word_pack>public_trackmembers</word_pack>
      <word_key>like_system_links_comments</word_key>
      <word_default>Like System (link comments) </word_default>
    </lang>
    <lang>
      <word_app>trackmembers</word_app>
      <word_pack>public_trackmembers</word_pack>
      <word_key>reputation_system_links</word_key>
      <word_default>Reputation Point (link)</word_default>
    </lang>
    <lang>
      <word_app>trackmembers</word_app>
      <word_pack>public_trackmembers</word_pack>
      <word_key>reputation_system_links_comments</word_key>
      <word_default>Reputation Point (link comments)</word_default>
    </lang>
    <lang>
      <word_app>trackmembers</word_app>
      <word_pack>public_trackmembers</word_pack>
      <word_key>follow_link</word_key>
      <word_default>Follow Link</word_default>
    </lang>
    <lang>
      <word_app>trackmembers</word_app>
      <word_pack>public_trackmembers</word_pack>
      <word_key>followed_link</word_key>
      <word_default>Followed a Link: %s</word_default>
    </lang>
    <lang>
      <word_app>trackmembers</word_app>
      <word_pack>public_trackmembers</word_pack>
      <word_key>liked_link</word_key>
      <word_default>Liked a Link: %s</word_default>
    </lang>
    <lang>
      <word_app>trackmembers</word_app>
      <word_pack>public_trackmembers</word_pack>
      <word_key>unliked_link</word_key>
      <word_default>Unliked a Link: %s</word_default>
    </lang>
    <lang>
      <word_app>trackmembers</word_app>
      <word_pack>public_trackmembers</word_pack>
      <word_key>link_reputation_point</word_key>
      <word_default>Gave a %s reputation point to a link: %s</word_default>
    </lang>
    <lang>
      <word_app>trackmembers</word_app>
      <word_pack>public_trackmembers</word_pack>
      <word_key>liked_link_comment</word_key>
      <word_default><![CDATA[Liked a <a href='%s'>comment</a> in link: %s]]></word_default>
    </lang>
    <lang>
      <word_app>trackmembers</word_app>
      <word_pack>public_trackmembers</word_pack>
      <word_key>link_comment_reputation_point</word_key>
      <word_default><![CDATA[Gave a %s reputation point to a <a href='%s'>comment</a> of link: %s]]></word_default>
    </lang>
    <lang>
      <word_app>trackmembers</word_app>
      <word_pack>public_trackmembers</word_pack>
      <word_key>added_link_comment</word_key>
      <word_default><![CDATA[Submitted a <a href='%s'>comment</a> to a link: %s]]></word_default>
    </lang>
    <lang>
      <word_app>trackmembers</word_app>
      <word_pack>public_trackmembers</word_pack>
      <word_key>calendar_actions</word_key>
      <word_default>Calendar Actions</word_default>
    </lang>
    <lang>
      <word_app>trackmembers</word_app>
      <word_pack>public_trackmembers</word_pack>
      <word_key>add_event</word_key>
      <word_default>Add Event</word_default>
    </lang>
    <lang>
      <word_app>trackmembers</word_app>
      <word_pack>public_trackmembers</word_pack>
      <word_key>added_event</word_key>
      <word_default>Event Added: %s</word_default>
    </lang>
    <lang>
      <word_app>trackmembers</word_app>
      <word_pack>public_trackmembers</word_pack>
      <word_key>edit_event</word_key>
      <word_default>Edit Event</word_default>
    </lang>
    <lang>
      <word_app>trackmembers</word_app>
      <word_pack>public_trackmembers</word_pack>
      <word_key>edited_event</word_key>
      <word_default>Event Edited: %s</word_default>
    </lang>
    <lang>
      <word_app>trackmembers</word_app>
      <word_pack>public_trackmembers</word_pack>
      <word_key>follow_event</word_key>
      <word_default>Follow Event</word_default>
    </lang>
    <lang>
      <word_app>trackmembers</word_app>
      <word_pack>public_trackmembers</word_pack>
      <word_key>followed_event</word_key>
      <word_default>Followed an Event: %s</word_default>
    </lang>
    <lang>
      <word_app>trackmembers</word_app>
      <word_pack>public_trackmembers</word_pack>
      <word_key>add_event_comment</word_key>
      <word_default>Submit Event Comment</word_default>
    </lang>
    <lang>
      <word_app>trackmembers</word_app>
      <word_pack>public_trackmembers</word_pack>
      <word_key>added_event_comment</word_key>
      <word_default><![CDATA[Submitted a <a href='%s'>comment</a> to an Event: %s]]></word_default>
    </lang>
    <lang>
      <word_app>trackmembers</word_app>
      <word_pack>public_trackmembers</word_pack>
      <word_key>like_system_event</word_key>
      <word_default>Like System (event)</word_default>
    </lang>
    <lang>
      <word_app>trackmembers</word_app>
      <word_pack>public_trackmembers</word_pack>
      <word_key>like_system_event_comments</word_key>
      <word_default>Like System (event comments) </word_default>
    </lang>
    <lang>
      <word_app>trackmembers</word_app>
      <word_pack>public_trackmembers</word_pack>
      <word_key>reputation_system_event</word_key>
      <word_default>Reputation Point (event)</word_default>
    </lang>
    <lang>
      <word_app>trackmembers</word_app>
      <word_pack>public_trackmembers</word_pack>
      <word_key>reputation_system_event_comments</word_key>
      <word_default>Reputation Point (event comments)</word_default>
    </lang>
    <lang>
      <word_app>trackmembers</word_app>
      <word_pack>public_trackmembers</word_pack>
      <word_key>liked_event</word_key>
      <word_default>Liked an Event: %s</word_default>
    </lang>
    <lang>
      <word_app>trackmembers</word_app>
      <word_pack>public_trackmembers</word_pack>
      <word_key>liked_event_comment</word_key>
      <word_default><![CDATA[Liked a <a href='%s'>comment</a> in an Event: %s]]></word_default>
    </lang>
    <lang>
      <word_app>trackmembers</word_app>
      <word_pack>public_trackmembers</word_pack>
      <word_key>event_reputation_point</word_key>
      <word_default>Gave a %s reputation point to an Event: %s</word_default>
    </lang>
    <lang>
      <word_app>trackmembers</word_app>
      <word_pack>public_trackmembers</word_pack>
      <word_key>event_comment_reputation_point</word_key>
      <word_default><![CDATA[Gave a %s reputation point to a <a href='%s'>comment</a> of the Event: %s]]></word_default>
    </lang>
    <lang>
      <word_app>trackmembers</word_app>
      <word_pack>public_trackmembers</word_pack>
      <word_key>forum_search</word_key>
      <word_default>Forums Search</word_default>
    </lang>
    <lang>
      <word_app>trackmembers</word_app>
      <word_pack>public_trackmembers</word_pack>
      <word_key>forum_search_done</word_key>
      <word_default><![CDATA[Used the search for the term '%s']]></word_default>
    </lang>
    <lang>
      <word_app>trackmembers</word_app>
      <word_pack>public_trackmembers</word_pack>
      <word_key>member_search</word_key>
      <word_default>Members Search</word_default>
    </lang>
    <lang>
      <word_app>trackmembers</word_app>
      <word_pack>public_trackmembers</word_pack>
      <word_key>member_search_done</word_key>
      <word_default><![CDATA[Used the search for the term '%s']]></word_default>
    </lang>
    <lang>
      <word_app>trackmembers</word_app>
      <word_pack>public_trackmembers</word_pack>
      <word_key>calendar_search</word_key>
      <word_default>Calendar Search</word_default>
    </lang>
    <lang>
      <word_app>trackmembers</word_app>
      <word_pack>public_trackmembers</word_pack>
      <word_key>search_done</word_key>
      <word_default><![CDATA[Used the search for the term '%s']]></word_default>
    </lang>
    <lang>
      <word_app>trackmembers</word_app>
      <word_pack>public_trackmembers</word_pack>
      <word_key>blog_search</word_key>
      <word_default>Entries Search</word_default>
    </lang>
    <lang>
      <word_app>trackmembers</word_app>
      <word_pack>public_trackmembers</word_pack>
      <word_key>downloads_search</word_key>
      <word_default>Files Search</word_default>
    </lang>
    <lang>
      <word_app>trackmembers</word_app>
      <word_pack>public_trackmembers</word_pack>
      <word_key>gallery_search</word_key>
      <word_default>Images/Medias Search</word_default>
    </lang>
    <lang>
      <word_app>trackmembers</word_app>
      <word_pack>public_trackmembers</word_pack>
      <word_key>advert_search</word_key>
      <word_default>Adverts Search</word_default>
    </lang>
    <lang>
      <word_app>trackmembers</word_app>
      <word_pack>public_trackmembers</word_pack>
      <word_key>links_search</word_key>
      <word_default>Links Search</word_default>
    </lang>
    <lang>
      <word_app>trackmembers</word_app>
      <word_pack>public_trackmembers</word_pack>
      <word_key>tutorials_search</word_key>
      <word_default>Tutorials Search</word_default>
    </lang>
    <lang>
      <word_app>trackmembers</word_app>
      <word_pack>public_trackmembers</word_pack>
      <word_key>videos_actions</word_key>
      <word_default>Videos Actions</word_default>
    </lang>
    <lang>
      <word_app>trackmembers</word_app>
      <word_pack>public_trackmembers</word_pack>
      <word_key>add_video</word_key>
      <word_default>Add Video</word_default>
    </lang>
    <lang>
      <word_app>trackmembers</word_app>
      <word_pack>public_trackmembers</word_pack>
      <word_key>added_video</word_key>
      <word_default>Video Added: %s</word_default>
    </lang>
    <lang>
      <word_app>trackmembers</word_app>
      <word_pack>public_trackmembers</word_pack>
      <word_key>edit_video</word_key>
      <word_default>Edit Video</word_default>
    </lang>
    <lang>
      <word_app>trackmembers</word_app>
      <word_pack>public_trackmembers</word_pack>
      <word_key>edited_video</word_key>
      <word_default>Video Edited: %s</word_default>
    </lang>
    <lang>
      <word_app>trackmembers</word_app>
      <word_pack>public_trackmembers</word_pack>
      <word_key>add_video_comment</word_key>
      <word_default>Submit Video Comment</word_default>
    </lang>
    <lang>
      <word_app>trackmembers</word_app>
      <word_pack>public_trackmembers</word_pack>
      <word_key>added_video_comment</word_key>
      <word_default><![CDATA[Submitted a <a href='%s'>comment</a> to a video: %s]]></word_default>
    </lang>
    <lang>
      <word_app>trackmembers</word_app>
      <word_pack>public_trackmembers</word_pack>
      <word_key>like_system_videos</word_key>
      <word_default>Like System (video)</word_default>
    </lang>
    <lang>
      <word_app>trackmembers</word_app>
      <word_pack>public_trackmembers</word_pack>
      <word_key>reputation_system_videos</word_key>
      <word_default>Reputation Point (video)</word_default>
    </lang>
    <lang>
      <word_app>trackmembers</word_app>
      <word_pack>public_trackmembers</word_pack>
      <word_key>liked_video</word_key>
      <word_default>Liked a Video: %s</word_default>
    </lang>
    <lang>
      <word_app>trackmembers</word_app>
      <word_pack>public_trackmembers</word_pack>
      <word_key>video_reputation_point</word_key>
      <word_default>Gave a %s reputation point to a Video: %s</word_default>
    </lang>
    <lang>
      <word_app>trackmembers</word_app>
      <word_pack>public_trackmembers</word_pack>
      <word_key>like_system_videos_comments</word_key>
      <word_default>Like System (video comments)</word_default>
    </lang>
    <lang>
      <word_app>trackmembers</word_app>
      <word_pack>public_trackmembers</word_pack>
      <word_key>reputation_system_videos_comments</word_key>
      <word_default>Reputation Point (video comments)</word_default>
    </lang>
    <lang>
      <word_app>trackmembers</word_app>
      <word_pack>public_trackmembers</word_pack>
      <word_key>liked_video_comment</word_key>
      <word_default><![CDATA[Liked a <a href='%s'>comment</a> in Video: %s]]></word_default>
    </lang>
    <lang>
      <word_app>trackmembers</word_app>
      <word_pack>public_trackmembers</word_pack>
      <word_key>video_comment_reputation_point</word_key>
      <word_default><![CDATA[Gave a %s reputation point to a <a href='%s'>comment</a> of Video: %s]]></word_default>
    </lang>
    <lang>
      <word_app>trackmembers</word_app>
      <word_pack>public_trackmembers</word_pack>
      <word_key>follow_video</word_key>
      <word_default>Follow Video</word_default>
    </lang>
    <lang>
      <word_app>trackmembers</word_app>
      <word_pack>public_trackmembers</word_pack>
      <word_key>followed_video</word_key>
      <word_default>Followed a Video: %s</word_default>
    </lang>
    <lang>
      <word_app>trackmembers</word_app>
      <word_pack>public_trackmembers</word_pack>
      <word_key>videos_search</word_key>
      <word_default>Videos Search</word_default>
    </lang>
    <lang>
      <word_app>trackmembers</word_app>
      <word_pack>public_trackmembers</word_pack>
      <word_key>export_to_pdf</word_key>
      <word_default>Export Logs to PDF</word_default>
    </lang>
    <lang>
      <word_app>trackmembers</word_app>
      <word_pack>public_trackmembers</word_pack>
      <word_key>tracking_logs_report</word_key>
      <word_default>Tracking Logs Report</word_default>
    </lang>
    <lang>
      <word_app>trackmembers</word_app>
      <word_pack>public_trackmembers</word_pack>
      <word_key>tracking_logs</word_key>
      <word_default>Tracking Logs</word_default>
    </lang>
    <lang>
      <word_app>trackmembers</word_app>
      <word_pack>public_trackmembers</word_pack>
      <word_key>tracking_logs_report_member_name</word_key>
      <word_default>Member Name</word_default>
    </lang>
    <lang>
      <word_app>trackmembers</word_app>
      <word_pack>public_trackmembers</word_pack>
      <word_key>tracking_logs_report_member_id</word_key>
      <word_default>Member ID</word_default>
    </lang>
    <lang>
      <word_app>trackmembers</word_app>
      <word_pack>public_trackmembers</word_pack>
      <word_key>tracking_logs_report_member_idid</word_key>
      <word_default>Member ID</word_default>
    </lang>
    <lang>
      <word_app>trackmembers</word_app>
      <word_pack>public_trackmembers</word_pack>
      <word_key>tracking_logs_report_member_group</word_key>
      <word_default>Member Group</word_default>
    </lang>
    <lang>
      <word_app>trackmembers</word_app>
      <word_pack>public_trackmembers</word_pack>
      <word_key>tracking_logs_report_member_joined</word_key>
      <word_default>Joined</word_default>
    </lang>
    <lang>
      <word_app>trackmembers</word_app>
      <word_pack>public_trackmembers</word_pack>
      <word_key>tracking_logs_report_member_joined</word_key>
      <word_default>Joined</word_default>
    </lang>
    <lang>
      <word_app>trackmembers</word_app>
      <word_pack>public_trackmembers</word_pack>
      <word_key>tracking_logs_report_page</word_key>
      <word_default>Page</word_default>
    </lang>
    <lang>
      <word_app>trackmembers</word_app>
      <word_pack>public_trackmembers</word_pack>
      <word_key>tracking_logs_report_pageof</word_key>
      <word_default>of</word_default>
    </lang>
  </languagegroup>
</languageexport>